vectoreasy/__init__.py
vectoreasy-0.0.1.dist-info/LICENSE
vectoreasy-0.0.1.dist-info/METADATA
vectoreasy-0.0.1.dist-info/WHEEL
vectoreasy-0.0.1.dist-info/top_level.txt
vectoreasy-0.0.1.dist-info/RECORD
