Metadata-Version: 2.1
Name: vectoreasy
Version: 0.0.1
Summary: Pacote python para plotagem de vetores em planos bidimensionais e espaços tridimensionais
Home-page: https://github.com/marcos-de-sousa/vectoreasy
Author: Marcos Paulo Alves de Sousa
Author-email: desousa.mpa@gmail.com
License: MIT License
Keywords: Pacote
Platform: UNKNOWN
License-File: LICENSE
Requires-Dist: numpy
Requires-Dist: matplotlib
